DataStructuresAndFunctionalProgrammingLectureNotesCornellCs3110/README.md
DataStructuresAndFunctionalProgrammingLectureNotesCornellCs3110/__init__.py
DataStructuresAndFunctionalProgrammingLectureNotesCornellCs3110/__main__.py
DataStructuresAndFunctionalProgrammingLectureNotesCornellCs3110/file.epub
DataStructuresAndFunctionalProgrammingLectureNotesCornellCs3110/index.html
DataStructuresAndFunctionalProgrammingLectureNotesCornellCs3110/css/__init__.py
DataStructuresAndFunctionalProgrammingLectureNotesCornellCs3110/css/annotations.css
DataStructuresAndFunctionalProgrammingLectureNotesCornellCs3110/css/main.css
DataStructuresAndFunctionalProgrammingLectureNotesCornellCs3110/css/normalize.css
DataStructuresAndFunctionalProgrammingLectureNotesCornellCs3110/css/popup.css
DataStructuresAndFunctionalProgrammingLectureNotesCornellCs3110/font/__init__.py
DataStructuresAndFunctionalProgrammingLectureNotesCornellCs3110/font/fontello.eot
DataStructuresAndFunctionalProgrammingLectureNotesCornellCs3110/font/fontello.svg
DataStructuresAndFunctionalProgrammingLectureNotesCornellCs3110/font/fontello.ttf
DataStructuresAndFunctionalProgrammingLectureNotesCornellCs3110/font/fontello.woff
DataStructuresAndFunctionalProgrammingLectureNotesCornellCs3110/img/__init__.py
DataStructuresAndFunctionalProgrammingLectureNotesCornellCs3110/img/annotator-glyph-sprite.png
DataStructuresAndFunctionalProgrammingLectureNotesCornellCs3110/img/annotator-icon-sprite.png
DataStructuresAndFunctionalProgrammingLectureNotesCornellCs3110/img/apple-touch-icon.png
DataStructuresAndFunctionalProgrammingLectureNotesCornellCs3110/img/cancelfullscreen.png
DataStructuresAndFunctionalProgrammingLectureNotesCornellCs3110/img/close.png
DataStructuresAndFunctionalProgrammingLectureNotesCornellCs3110/img/fullscreen.png
DataStructuresAndFunctionalProgrammingLectureNotesCornellCs3110/img/loader.gif
DataStructuresAndFunctionalProgrammingLectureNotesCornellCs3110/img/menu-icon.png
data_structures_and_functional_programming_lecture_notes_cornell_cs3110-2024.3.2.0.dist-info/METADATA
data_structures_and_functional_programming_lecture_notes_cornell_cs3110-2024.3.2.0.dist-info/WHEEL
data_structures_and_functional_programming_lecture_notes_cornell_cs3110-2024.3.2.0.dist-info/entry_points.txt
data_structures_and_functional_programming_lecture_notes_cornell_cs3110-2024.3.2.0.dist-info/top_level.txt
data_structures_and_functional_programming_lecture_notes_cornell_cs3110-2024.3.2.0.dist-info/RECORD
